tfjeeves/README.md
tfjeeves/__init__.py
tfjeeves/callbacks/__init__.py
tfjeeves/callbacks/core.py
tfjeeves/callbacks/loggers.py
tfjeeves/core/__init__.py
tfjeeves/core/dataloader.py
tfjeeves/core/dataset.py
tfjeeves/core/experiment.py
tfjeeves/core/image_stats.py
tfjeeves/core/inference.py
tfjeeves/core/iterable.py
tfjeeves/losses/__init__.py
tfjeeves/losses/triplet.py
tfjeeves/models/__init__.py
tfjeeves/models/classification.py
tfjeeves/models/metric/__init__.py
tfjeeves/models/metric/baseline.py
tfjeeves/models/metric/finetuning.py
tfjeeves/models/metric/resnet50.py
tfjeeves/models/regression/__init__.py
tfjeeves/models/regression/baseline.py
tfjeeves/models/regression/effnetb4.py
tfjeeves/models/regression/mobilenetv2.py
tfjeeves/models/regression/resnet101.py
tfjeeves/models/regression/resnet50.py
tfjeeves/models/triplet/__init__.py
tfjeeves/models/triplet/classifier.py
tfjeeves/models/triplet/effnetb3.py
tfjeeves/models/triplet/effnetb7.py
tfjeeves/plotting/__init__.py
tfjeeves/plotting/plotting.py
tfjeeves/tests/__init__.py
tfjeeves/tests/fixtures/presize/categoryA/subcategoryA/subsubcategoryA/7eef0827405449.563649cb75fe7.jpg
tfjeeves/tests/fixtures/presize/categoryA/subcategoryA/subsubcategoryB/1920x1080.jpeg
tfjeeves/tests/fixtures/presize/categoryA/subcategoryB/subsubcategoryC/aa2f5128119449.5636feb6a3573.png
tfjeeves/tests/fixtures/presize/categoryA/subcategoryB/subsubcategoryC/b03a0723813299.5632938730540.jpg
tfjeeves/tests/fixtures/presize/categoryA/subcategoryB/subsubcategoryD/1299437663_f38d372efc.jpg
tfjeeves/tests/fixtures/presize/categoryB/subcategoryA/subsubcategoryA/340e2916546901.562ad9fea9366.png
tfjeeves/tests/fixtures/presize/categoryB/subcategoryA/subsubcategoryA/758a13087ff64274856aa0f99c209bd2.jpeg
tfjeeves/tests/fixtures/presize/categoryB/subcategoryA/subsubcategoryB/29404430108_be59fcd0e2_b.jpg
tfjeeves/tests/fixtures/presize/categoryB/subcategoryA/subsubcategoryB/7359c429008505.55dd997fcf361.png
tfjeeves-0.2.6.dist-info/entry_points.txt
tfjeeves-0.2.6.dist-info/WHEEL
tfjeeves-0.2.6.dist-info/METADATA
tfjeeves-0.2.6.dist-info/RECORD
